[
  {
    "chunk": 0,
    "train_gmean": 1.0,
    "test_gmean": 1.0,
    "test_f1": 1.0
  },
  {
    "chunk": 1,
    "train_gmean": 1.0,
    "test_gmean": 1.0,
    "test_f1": 1.0
  },
  {
    "chunk": 2,
    "train_gmean": 1.0,
    "test_gmean": 0.6770524136997108,
    "test_f1": 0.6811434206248068
  },
  {
    "chunk": 3,
    "train_gmean": 0.660734130766676,
    "test_gmean": 0.6522731418514721,
    "test_f1": 0.6682057019560924
  },
  {
    "chunk": 4,
    "train_gmean": 0.6474157577198507,
    "test_gmean": 0.6351333776723707,
    "test_f1": 0.6554849221476725
  }
]