[
  {
    "logical_ops": [
      "AND",
      "AND",
      "AND",
      "AND",
      "AND",
      "AND",
      "AND",
      "AND",
      "AND",
      "AND",
      "AND",
      "AND",
      "AND",
      "AND",
      "AND",
      "AND",
      "AND",
      "AND",
      "AND",
      "AND",
      "AND",
      "AND",
      "AND",
      "AND",
      "AND",
      "AND",
      "AND",
      "AND",
      "AND",
      "AND",
      "AND",
      "AND",
      "AND",
      "AND",
      "AND",
      "AND",
      "AND",
      "AND",
      "AND",
      "AND",
      "AND",
      "AND",
      "AND",
      "AND",
      "AND",
      "AND",
      "AND",
      "AND",
      "AND",
      "AND",
      "AND",
      "AND",
      "AND",
      "AND",
      "AND",
      "AND",
      "AND",
      "AND",
      "AND",
      "AND",
      "AND",
      "AND",
      "AND",
      "AND"
    ],
    "comparison_ops": [
      "<=",
      "<",
      ">",
      ">",
      ">",
      ">",
      ">",
      "<=",
      "<=",
      "<=",
      ">",
      "<=",
      "<=",
      ">",
      "<=",
      ">",
      "<=",
      ">",
      "<=",
      "<=",
      ">",
      "<=",
      ">",
      ">",
      ">",
      "<=",
      "<=",
      "<=",
      ">",
      "<=",
      ">",
      ">",
      "<=",
      "<=",
      "<=",
      "<=",
      ">",
      "<=",
      ">",
      "<=",
      ">",
      "<=",
      ">",
      "<=",
      ">",
      "<=",
      ">",
      ">",
      ">",
      ">",
      "<=",
      "<=",
      ">",
      "<=",
      ">",
      ">",
      "<=",
      "<=",
      "<=",
      ">",
      "<=",
      ">",
      "<=",
      ">",
      ">",
      ">",
      "<=",
      "<=",
      ">",
      "<=",
      "<=",
      ">",
      ">",
      ">",
      ">",
      "<=",
      ">"
    ],
    "numeric_thresholds": [
      25494.189453125,
      1.0454054146694878,
      100085.46875,
      39.5,
      59.5,
      100085.46875,
      39.5,
      59.5,
      125024.5234375,
      124823.06640625,
      25494.189453125,
      100085.46875,
      50455.421875,
      59.5,
      100085.46875,
      25494.189453125,
      38.5,
      50080.419921875,
      98772.94140625,
      124823.06640625,
      25494.189453125,
      100085.46875,
      50455.421875,
      39.5,
      214663.9921875,
      77.5,
      1164799.5,
      124823.06640625,
      25494.189453125,
      100085.46875,
      50455.421875,
      39.5,
      214663.9921875,
      201140.0703125,
      17.5,
      79374.0859375,
      476844.421875,
      124823.06640625,
      25494.189453125,
      100085.46875,
      50455.421875,
      39.5,
      99431.53515625,
      124823.06640625,
      25494.189453125,
      100085.46875,
      50455.421875,
      39.5,
      214663.9921875,
      77.5,
      77676.33203125,
      124823.06640625,
      25494.189453125,
      100085.46875,
      50455.421875,
      39.5,
      214663.9921875,
      201140.0703125,
      17.5,
      79374.0859375,
      124823.06640625,
      25494.189453125,
      100085.46875,
      50455.421875,
      39.5,
      214663.9921875,
      77.5,
      1164799.5,
      957086.84375,
      1.5,
      100085.46875,
      25494.189453125,
      38.5,
      201140.0703125,
      59.5,
      74273.19921875,
      27601.55078125
    ],
    "categorical_values_used": [],
    "features": [
      "loan",
      "elevel",
      "age",
      "commission",
      "car",
      "salary",
      "hvalue"
    ]
  },
  {
    "logical_ops": [
      "AND",
      "AND",
      "AND",
      "AND",
      "AND",
      "AND",
      "AND",
      "AND",
      "AND",
      "AND",
      "AND",
      "AND",
      "AND",
      "AND",
      "AND",
      "AND",
      "AND",
      "AND",
      "AND",
      "AND",
      "AND",
      "AND",
      "AND",
      "AND",
      "AND",
      "AND",
      "AND",
      "AND",
      "AND",
      "AND",
      "AND",
      "AND",
      "AND",
      "AND",
      "AND",
      "AND",
      "AND",
      "AND",
      "AND",
      "AND",
      "AND",
      "AND",
      "AND"
    ],
    "comparison_ops": [
      "<=",
      "<=",
      "<=",
      "<=",
      "<=",
      "<=",
      ">",
      "<=",
      ">",
      "<=",
      "<=",
      "<=",
      "<=",
      ">",
      ">=",
      "<=",
      ">",
      ">",
      "<=",
      ">",
      "<=",
      "<=",
      ">",
      "<",
      ">",
      "<",
      "<=",
      "<=",
      ">",
      ">",
      "<=",
      ">",
      "<=",
      ">",
      "<=",
      "<=",
      "<=",
      "<=",
      "<=",
      ">",
      ">",
      "<",
      ">",
      ">",
      "<=",
      ">",
      ">",
      "<=",
      ">",
      ">=",
      "<=",
      ">",
      "<=",
      ">",
      "<=",
      ">",
      "<=",
      "<="
    ],
    "numeric_thresholds": [
      50037.828125,
      59.5,
      20.5,
      50037.828125,
      59.5,
      21264.388671875,
      124934.1171875,
      1.5,
      124934.1171875,
      13706.62548828125,
      50037.828125,
      59.5,
      12829.10009765625,
      31323.559745600418,
      5.161482827533245,
      50037.828125,
      59.5,
      24973.75,
      124934.1171875,
      50037.828125,
      58.5,
      96739.50627703118,
      75535.375,
      124934.1171875,
      70377.82563144002,
      99839.890625,
      39.5,
      124934.1171875,
      50037.828125,
      58.5,
      75072.859375,
      60.5,
      124934.1171875,
      50037.828125,
      58.5,
      100055.1328125,
      74211.9296875,
      39.5,
      50037.828125,
      59.5,
      24973.75,
      50037.828125,
      59.5,
      24973.75,
      124934.1171875,
      50037.828125,
      99839.890625,
      59.5,
      39.5,
      2.5,
      124934.1171875,
      50037.828125,
      99839.890625,
      39.5,
      442513.953125,
      52465.4921875,
      62.5,
      16288.92822265625
    ],
    "categorical_values_used": [],
    "features": [
      "loan",
      "age",
      "commission",
      "hyears",
      "car",
      "salary",
      "hvalue"
    ]
  },
  {
    "logical_ops": [
      "AND",
      "AND",
      "AND",
      "AND",
      "AND",
      "AND",
      "AND",
      "AND",
      "AND",
      "AND",
      "AND",
      "AND",
      "AND",
      "AND",
      "AND",
      "AND",
      "AND",
      "AND",
      "AND",
      "AND",
      "AND",
      "AND",
      "AND",
      "AND",
      "AND",
      "AND",
      "AND",
      "AND",
      "AND",
      "AND",
      "AND",
      "AND",
      "AND",
      "AND"
    ],
    "comparison_ops": [
      ">",
      "<=",
      ">",
      ">",
      "<=",
      ">",
      "<=",
      "<=",
      ">",
      ">",
      "<=",
      ">",
      ">",
      "<=",
      ">",
      "<=",
      ">",
      "<=",
      "<=",
      ">",
      "<=",
      ">",
      "<=",
      ">",
      ">",
      ">",
      "<=",
      ">",
      "<=",
      "<=",
      "<=",
      ">",
      "<=",
      ">",
      ">",
      "<=",
      "<=",
      ">",
      ">",
      "<=",
      ">",
      ">",
      "<=",
      ">",
      "<=",
      "<="
    ],
    "numeric_thresholds": [
      124847.26953125,
      21.5,
      124847.26953125,
      32581.596587592896,
      1.5,
      124847.26953125,
      1.5,
      28074.4541015625,
      59.5,
      25085.6806640625,
      124847.26953125,
      28074.4541015625,
      70691.58730373473,
      59.5,
      39.5,
      124847.26953125,
      28074.4541015625,
      101385.99609375,
      50004.064453125,
      59.5,
      124847.26953125,
      50004.064453125,
      99724.734375,
      39.5,
      59.5,
      5404.21728515625,
      124847.26953125,
      50004.064453125,
      99724.734375,
      39.5,
      124847.26953125,
      28074.4541015625,
      101385.99609375,
      50004.064453125,
      39.5,
      937070.3125,
      6.5,
      45102.45703125,
      59.0,
      28074.4541015625,
      59.5,
      25085.6806640625,
      124847.26953125,
      50004.064453125,
      99724.734375,
      39.5
    ],
    "categorical_values_used": [],
    "features": [
      "age",
      "commission",
      "hyears",
      "car",
      "zipcode",
      "salary",
      "hvalue"
    ]
  },
  {
    "logical_ops": [
      "AND",
      "AND",
      "AND",
      "AND",
      "AND",
      "AND",
      "AND",
      "OR",
      "OR",
      "AND",
      "AND",
      "AND",
      "AND",
      "AND",
      "AND",
      "AND",
      "AND",
      "AND",
      "AND",
      "AND",
      "AND",
      "AND",
      "AND",
      "AND",
      "AND",
      "AND",
      "AND",
      "AND",
      "AND",
      "AND",
      "AND",
      "AND",
      "AND",
      "AND",
      "AND",
      "AND",
      "AND",
      "AND",
      "AND",
      "AND",
      "AND",
      "AND",
      "AND",
      "AND",
      "AND"
    ],
    "comparison_ops": [
      ">",
      "<=",
      ">",
      "<=",
      ">",
      "<=",
      ">",
      "<=",
      ">",
      "<=",
      ">",
      "<=",
      ">",
      "<=",
      "<=",
      ">",
      ">=",
      "<=",
      ">",
      "<=",
      "<=",
      ">",
      "<=",
      ">",
      "<=",
      "<=",
      "<=",
      ">",
      "<=",
      ">",
      "<=",
      "<=",
      ">",
      "<=",
      ">",
      ">",
      ">",
      "<=",
      ">",
      ">",
      "<=",
      ">",
      "<=",
      ">",
      ">",
      "<=",
      ">",
      "<=",
      ">",
      "<=",
      ">",
      ">",
      "<=",
      "<=",
      ">",
      "<=",
      ">",
      "<=",
      ">",
      "<=",
      ">",
      ">"
    ],
    "numeric_thresholds": [
      124852.984375,
      0.5,
      124852.984375,
      20.5,
      93198.14517152097,
      1.5,
      124852.984375,
      27089.12109375,
      124852.984375,
      1.5,
      124852.984375,
      1.5,
      124852.984375,
      125591.92578125,
      7.709053316582625,
      787743.7963502221,
      5.8970890271851895,
      124852.984375,
      25475.154296875,
      98395.375,
      39.5,
      49959.708984375,
      124852.984375,
      49850.048828125,
      98395.375,
      39.5,
      124852.984375,
      25475.154296875,
      99988.0,
      49690.51171875,
      40.5,
      124852.984375,
      25475.154296875,
      98395.375,
      59.5,
      5329.3271484375,
      0.5,
      124852.984375,
      25475.154296875,
      98395.375,
      59.5,
      39.5,
      124852.984375,
      49850.048828125,
      98395.375,
      59.5,
      39.5,
      124852.984375,
      25475.154296875,
      99988.0,
      49690.51171875,
      40.5,
      55518.013671875,
      60.5,
      77767.24609375,
      124852.984375,
      98395.375,
      59.5,
      41.5,
      49850.048828125,
      59.5,
      25238.865234375
    ],
    "categorical_values_used": [],
    "features": [
      "age",
      "hyears",
      "commission",
      "car",
      "zipcode",
      "hvalue",
      "salary"
    ]
  },
  {
    "logical_ops": [
      "AND",
      "AND",
      "AND",
      "AND",
      "AND",
      "AND",
      "AND",
      "AND",
      "AND",
      "AND",
      "AND",
      "AND",
      "AND",
      "AND",
      "AND",
      "AND",
      "AND",
      "AND",
      "AND",
      "AND",
      "AND",
      "AND",
      "AND",
      "AND",
      "AND",
      "AND",
      "AND",
      "AND",
      "AND",
      "AND",
      "AND",
      "AND",
      "AND",
      "AND"
    ],
    "comparison_ops": [
      ">",
      "<=",
      "<=",
      ">",
      "<=",
      ">",
      "<=",
      "<=",
      ">",
      "<=",
      "<=",
      ">",
      "<=",
      ">",
      ">",
      "<=",
      ">",
      "<=",
      ">",
      "<=",
      ">",
      "<=",
      ">",
      "<=",
      ">",
      "<=",
      ">",
      "<=",
      ">",
      ">",
      ">",
      "<=",
      ">",
      "<=",
      ">",
      "<=",
      "<=",
      ">",
      "<=",
      ">",
      ">",
      "<=",
      ">",
      ">"
    ],
    "numeric_thresholds": [
      124667.29296875,
      125129.81640625,
      46972.255859375,
      59.5,
      24889.7646484375,
      124667.29296875,
      21.5,
      124667.29296875,
      46972.255859375,
      100064.8125,
      39.5,
      50003.376953125,
      124667.29296875,
      46972.255859375,
      100064.8125,
      59.5,
      39.5,
      124667.29296875,
      46972.255859375,
      100064.8125,
      39.5,
      66.5,
      73694.0078125,
      59.5,
      75254.05859375,
      124667.29296875,
      46972.255859375,
      100064.8125,
      39.5,
      66.5,
      5351.4716796875,
      124667.29296875,
      46972.255859375,
      100064.8125,
      39.5,
      66.5,
      73694.0078125,
      59.5,
      46972.255859375,
      59.5,
      24889.7646484375,
      46972.255859375,
      59.5,
      24889.7646484375
    ],
    "categorical_values_used": [],
    "features": [
      "age",
      "salary",
      "commission"
    ]
  }
]